MANIFEST.in
README.md
setup.py
ceotr_web_common.egg-info/PKG-INFO
ceotr_web_common.egg-info/SOURCES.txt
ceotr_web_common.egg-info/dependency_links.txt
ceotr_web_common.egg-info/top_level.txt
ceotr_web_common.egg-info/zip-safe
web_common/__init__.py
web_common/static/web-common/npm-debug.log
web_common/static/web-common/package-lock.json
web_common/static/web-common/package.json
web_common/static/web-common/tsconfig.json
web_common/static/web-common/directives/directives.js
web_common/static/web-common/directives/ng-wagtail-stream.html
web_common/static/web-common/directives/wagtail-stream.html
web_common/static/web-common/directives/wagtailStream.component.ts
web_common/static/web-common/helpers/dom-helpers.d.ts
web_common/static/web-common/helpers/dom-helpers.js
web_common/static/web-common/helpers/extensions.d.ts
web_common/static/web-common/helpers/extensions.js
web_common/static/web-common/helpers/math.js
web_common/static/web-common/helpers/math.ts
web_common/static/web-common/helpers/router-helpers.d.ts
web_common/static/web-common/helpers/router-helpers.js
web_common/static/web-common/helpers/styles.js
web_common/static/web-common/libs/angular-leaflet-directive/0.10.0/angular-leaflet-directive.min.js
web_common/static/web-common/libs/angular-leaflet-directive/0.10.0/angular-leaflet-directive.no-header.js
web_common/static/web-common/libs/angular-marked/README.md
web_common/static/web-common/libs/angular-marked/package.json
web_common/static/web-common/libs/angular-marked/dist/angular-marked.js
web_common/static/web-common/libs/angular-marked/dist/angular-marked.min.js
web_common/static/web-common/libs/angular-marked/lib/angular-marked.js
web_common/static/web-common/libs/angular-marked/lib/strip-indent.js
web_common/static/web-common/libs/angular-simple-logger/README.md
web_common/static/web-common/libs/angular-simple-logger/package.json
web_common/static/web-common/libs/angular-simple-logger/dist/angular-simple-logger.js
web_common/static/web-common/libs/angular-simple-logger/dist/angular-simple-logger.light.js
web_common/static/web-common/libs/angular-simple-logger/dist/angular-simple-logger.light.min.js
