Metadata-Version: 2.1
Name: ceotr-web-common
Version: 1.0.1
Summary: Common web assets
Home-page: https://gitlab.oceantrack.org/ofi/web-common.git
Author: CEOTR
Author-email: support@ceotr.ca
License: UNKNOWN
Platform: UNKNOWN
